{
    "id": "eebb860e-ba32-47bf-8b90-506dda0cadfb",
    "schema": "https://metadata.datadrivendiscovery.org/schemas/v0/pipeline.json",
    "created": "2019-06-17T20:58:24.118701Z",
    "inputs": [
        {
            "name": "inputs"
        }
    ],
    "outputs": [
        {
            "data": "steps.1.produce",
            "name": "output"
        }
    ],
    "steps": [
        {
            "type": "PRIMITIVE",
            "primitive": {
                "id": "79012210-2463-4f94-9da6-11bdc5a7e6c4",
                "version": "0.1.0",
                "python_path": "d3m.primitives.data_transformation.load_single_graph.DistilSingleGraphLoader",
                "name": "Load single graph and dataframe into a parseable object",
                "digest": "9893cb98b9eef3357dbd2caa82197afecab77d9acf135712c74b4ce4d57976b3"
            },
            "arguments": {
                "inputs": {
                    "type": "CONTAINER",
                    "data": "inputs.0"
                }
            },
            "outputs": [
                {
                    "id": "produce"
                },
                {
                    "id": "produce_target"
                }
            ]
        },
        {
            "type": "PRIMITIVE",
            "primitive": {
                "id": "fc138210-c317-4528-81ae-5eed3a1a0267",
                "version": "0.1.0",
                "python_path": "d3m.primitives.data_transformation.link_prediction.DistilLinkPrediction",
                "name": "LinkPrediction",
                "digest": "daa9516aa289abed216b19c15af8fa112fc786e2cd4a0392202feae3b9a7b7c2"
            },
            "arguments": {
                "inputs": {
                    "type": "CONTAINER",
                    "data": "steps.0.produce"
                },
                "outputs": {
                    "type": "CONTAINER",
                    "data": "steps.0.produce_target"
                }
            },
            "outputs": [
                {
                    "id": "produce"
                }
            ],
            "hyperparams": {
                "metric": {
                    "type": "VALUE",
                    "data": "accuracy"
                }
            }
        }
    ],
    "digest": "86601d8afb5821013cb4935d7958d2fc15910966720e9b6701764e9618a3d9e6"
}
