{
    "id": "86d1e046-4b88-4666-93bc-24b62101d242",
    "schema": "https://metadata.datadrivendiscovery.org/schemas/v0/pipeline.json",
    "created": "2019-06-15T16:50:15.386816Z",
    "inputs": [
        {
            "name": "inputs"
        }
    ],
    "outputs": [
        {
            "data": "steps.1.produce",
            "name": "output"
        }
    ],
    "steps": [
        {
            "type": "PRIMITIVE",
            "primitive": {
                "id": "79012210-2463-4f94-9da6-11bdc5a7e6c4",
                "version": "0.1.0",
                "python_path": "d3m.primitives.data_transformation.load_single_graph.DistilSingleGraphLoader",
                "name": "Load single graph and dataframe into a parseable object",
                "digest": "09fe82afd90cccf574b41be164818cdddc37ba270c3b6183e7b79366d63a8ef4"
            },
            "arguments": {
                "inputs": {
                    "type": "CONTAINER",
                    "data": "inputs.0"
                }
            },
            "outputs": [
                {
                    "id": "produce"
                },
                {
                    "id": "produce_target"
                }
            ]
        },
        {
            "type": "PRIMITIVE",
            "primitive": {
                "id": "0130828c-1ac0-47a9-a167-f05bae5a3146",
                "version": "0.1.0",
                "python_path": "d3m.primitives.data_transformation.vertex_nomination.DistilVertexNomination",
                "name": "VertexNomination",
                "digest": "53ae561acbf57b6dd88a4c57b7431300abd8974f0c4d23d4f97f161e5b7ba1e2"
            },
            "arguments": {
                "inputs": {
                    "type": "CONTAINER",
                    "data": "steps.0.produce"
                },
                "outputs": {
                    "type": "CONTAINER",
                    "data": "steps.0.produce_target"
                }
            },
            "outputs": [
                {
                    "id": "produce"
                }
            ],
            "hyperparams": {
                "metric": {
                    "type": "VALUE",
                    "data": "accuracy"
                }
            }
        }
    ],
    "digest": "cd2d77b8d2f08bec7c8bee0a205b59f2aef099a8a2007cd996e089ba3acc01e7"
}
